README.rst
setup.py
paytm/Checksum.py
paytm/__init__.py
paytm/payments.py
paytm/paymentstatus.py
paytm.egg-info/PKG-INFO
paytm.egg-info/SOURCES.txt
paytm.egg-info/dependency_links.txt
paytm.egg-info/not-zip-safe
paytm.egg-info/requires.txt
paytm.egg-info/top_level.txt