Metadata-Version: 1.0
Name: paytm
Version: 0.1.7
Summary: paytm payment gateway
Home-page: http://github.com/harishbisht/paytm
Author: Harish Bisht
Author-email: harish@pickrr.com
License: MIT
Platform: UNKNOWN
